{
  "id": "4da8ca3d-86c2-40ba-84c0-5ea949293b9b",
  "created_on": "2021-03-04T12:02:44+00:00",
  "changed_on": "2021-03-04T12:10:37+00:00",
  "body": "Post",
  "description": null,
  "label": "PublicationModel",
  "status": "published",
  "stories": false,
  "timelines": false,
  "allow_stories": false,
  "channels": false,
  "allow_channels": false,
  "container_required": false,
  "channels_required": false,
  "seo_score": false,
  "ab_testing": false,
  "versioning": false,
  "slug": null,
  "for": null,
  "fields": [
    {
      "type": "Text",
      "required": false,
      "preview": true,
      "body": "Title",
      "view": "single_line",
      "localized": true,
      "id": "7aa96451-d3b5-41e9-b012-77f66dd2213b",
      "api_id": "title",
      "created_on": "2021-03-04T12:02:49+00:00",
      "changed_on": "2021-03-04T12:02:49+00:00",
      "label": "PublicationModelField",
      "title": false,
      "seo_title": false,
      "seo_description": false,
      "description": null,
      "disable_editing": false,
      "appearance": "single_line",
      "accept_restrictions": null,
      "no_html": false
    },
    {
      "type": "Text",
      "required": false,
      "preview": true,
      "body": "Summary",
      "view": "textarea",
      "localized": true,
      "id": "ea6a35ca-5a39-4786-9cf7-15e917a0dcf4",
      "api_id": "summary",
      "created_on": "2021-03-04T12:02:59+00:00",
      "changed_on": "2021-03-04T12:02:59+00:00",
      "label": "PublicationModelField",
      "title": false,
      "seo_title": false,
      "seo_description": false,
      "description": null,
      "disable_editing": false,
      "appearance": "textarea",
      "accept_restrictions": null,
      "no_html": false
    },
    {
      "accept": [
        "bold",
        "italic",
        "underline",
        "unordered-list",
        "ordered-list",
        "link",
        "table"
      ],
      "preview": true,
      "view": "html_editor",
      "type": "Text",
      "required": false,
      "body": "Content",
      "localized": true,
      "id": "cd31e930-a08c-4740-903e-5c41fcd1c555",
      "api_id": "content",
      "created_on": "2021-03-04T12:04:36+00:00",
      "changed_on": "2021-03-04T12:04:36+00:00",
      "label": "PublicationModelField",
      "title": false,
      "seo_title": false,
      "seo_description": false,
      "description": null,
      "disable_editing": false,
      "appearance": "html_editor",
      "accept_restrictions": null,
      "no_html": false
    },
    {
      "accept": ["photo"],
      "max": "1",
      "preview": true,
      "type": "Asset",
      "min": "1",
      "required": true,
      "body": "Cover Image",
      "localized": true,
      "id": "cfca83f3-5a73-4567-bde1-4adeb57915d0",
      "api_id": "cover",
      "created_on": "2021-03-04T12:03:17+00:00",
      "changed_on": "2021-03-04T12:03:17+00:00",
      "label": "PublicationModelField",
      "title": false,
      "seo_title": false,
      "seo_description": false,
      "description": null,
      "disable_editing": false,
      "appearance": null,
      "accept_restrictions": null,
      "presets_change_required": false
    },
    {
      "type": "Publication",
      "min": "1",
      "required": true,
      "max": "1",
      "preview": false,
      "body": "Author",
      "localized": true,
      "id": "8308380f-af0a-40e7-ae30-33b2f7ce93d9",
      "api_id": "author",
      "created_on": "2021-03-04T12:04:51+00:00",
      "changed_on": "2021-03-04T12:04:51+00:00",
      "label": "PublicationModelField",
      "title": false,
      "seo_title": false,
      "seo_description": false,
      "description": null,
      "disable_editing": false,
      "appearance": null,
      "accept_restrictions": null
    },
    {
      "type": "Slug",
      "description": "The slug is generated automatically. You can change the slug, as long as it is unique.",
      "body": "Slug",
      "id": "7214e365-1b4c-4de3-8412-e311250fb4da",
      "api_id": null,
      "created_on": "2021-03-04T12:03:32+00:00",
      "changed_on": "2021-03-04T12:03:32+00:00",
      "label": "PublicationModelField",
      "title": false,
      "seo_title": false,
      "seo_description": false,
      "required": false,
      "localized": false,
      "preview": false,
      "disable_editing": false,
      "appearance": null,
      "accept_restrictions": null
    }
  ]
}
